{"error": null, "issues": [{"address": 150, "code": "for(uint i=0;i<350;i++) {\n                listAddresses.push(msg.sender);\n            }", "contract": "DosOneFunc", "description": "Potential denial-of-service if block gas limit is reached.\nA storage modification is executed in a loop.", "filename": "/home/ubuntu/curated-vulnerable-contracts/swc-128/dos_simple.sol", "function": "ifillArray()", "lineno": 17, "max_gas_used": 132833, "min_gas_used": 31463, "severity": "Low", "sourceMap": "400:87", "swc-id": "128", "title": "Potential denial-of-service if block gas limit is reached", "tx_sequence": null}], "success": true}
Command exited with non-zero status 1
5.32user 0.59system 0:07.04elapsed 84%CPU (0avgtext+0avgdata 139092maxresident)k
0inputs+9808outputs (0major+29844minor)pagefaults 0swaps
